{"results": [{"gender": "male", "name": {"title": "Mr", "first": "Eugenio", "last": "Rodr\u00edguez"}, "location": {"street": {"number": 44, "name": "Calle de \u00c1ngel Garc\u00eda"}, "city": "Santa Cruz de Tenerife", "state": "Comunidad Valenciana", "country": "Spain", "postcode": 87362, "coordinates": {"latitude": "-35.3662", "longitude": "-140.1106"}, "timezone": {"offset": "-7:00", "description": "Mountain Time (US & Canada)"}}, "email": "eugenio.rodriguez@example.com", "login": {"uuid": "5c30bc9d-10da-428f-ae5f-0feae807279b", "username": "goldenwolf111", "password": "toad", "salt": "fc2NiI9y", "md5": "c0ebebd78d321f698441deb827191bed", "sha1": "37f7d5a8c4d4e426670e19168347b173c8c1c4b2", "sha256": "faec0f833c0092f12b6a8c17a0a8a68b9a6e640c3f26861f9ad6fc4fd74c3053"}, "dob": {"date": "2000-09-24T06:52:34.216Z", "age": 23}, "registered": {"date": "2020-02-25T16:44:56.415Z", "age": 3}, "phone": "995-041-457", "cell": "643-532-440", "id": {"name": "DNI", "value": "24909615-A"}, "picture": {"large": "https://randomuser.me/api/portraits/men/67.jpg", "medium": "https://randomuser.me/api/portraits/med/men/67.jpg", "thumbnail": "https://randomuser.me/api/portraits/thumb/men/67.jpg"}, "nat": "ES"}], "info": {"seed": "0217efa6f958a301", "results": 1, "page": 1, "version": "1.4"}}